shopify_partners_sdk/__init__.py
shopify_partners_sdk/client/__init__.py
shopify_partners_sdk/client/auth.py
shopify_partners_sdk/client/base.py
shopify_partners_sdk/client/field_based_client.py
shopify_partners_sdk/client/rate_limiter.py
shopify_partners_sdk/client/retry.py
shopify_partners_sdk/config/__init__.py
shopify_partners_sdk/config/defaults.py
shopify_partners_sdk/config/settings.py
shopify_partners_sdk/exceptions/__init__.py
shopify_partners_sdk/exceptions/auth.py
shopify_partners_sdk/exceptions/base.py
shopify_partners_sdk/exceptions/graphql.py
shopify_partners_sdk/exceptions/rate_limit.py
shopify_partners_sdk/exceptions/validation.py
shopify_partners_sdk/models/__init__.py
shopify_partners_sdk/models/base.py
shopify_partners_sdk/models/enums.py
shopify_partners_sdk/models/inputs.py
shopify_partners_sdk/models/objects/__init__.py
shopify_partners_sdk/models/objects/app.py
shopify_partners_sdk/models/objects/organization.py
shopify_partners_sdk/models/objects/shop.py
shopify_partners_sdk/models/objects/transaction.py
shopify_partners_sdk/models/objects/version.py
shopify_partners_sdk/models/scalars.py
shopify_partners_sdk/mutations/__init__.py
shopify_partners_sdk/mutations/base.py
shopify_partners_sdk/mutations/custom_builders.py
shopify_partners_sdk/pagination/__init__.py
shopify_partners_sdk/pagination/cursor.py
shopify_partners_sdk/pagination/iterator.py
shopify_partners_sdk/py.typed
shopify_partners_sdk/queries/__init__.py
shopify_partners_sdk/queries/base.py
shopify_partners_sdk/queries/custom_builders.py
shopify_partners_sdk/queries/fields.py
shopify_partners_sdk/version.py
shopify_partners_sdk-0.3.2.dist-info/METADATA
shopify_partners_sdk-0.3.2.dist-info/WHEEL
shopify_partners_sdk-0.3.2.dist-info/licenses/LICENSE
shopify_partners_sdk-0.3.2.dist-info/RECORD
