Metadata-Version: 2.4
Name: shopify-partners-sdk
Version: 0.3.2
Summary: Modern Python GraphQL SDK for Shopify Partners API
License: MIT
License-File: LICENSE
Keywords: shopify,partners,graphql,sdk,api,apps
Author: Amit Ray
Author-email: mail@amitray.dev
Maintainer: Amit Ray
Maintainer-email: mail@amitray.dev
Requires-Python: >=3.9,<4.0
Classifier: Development Status :: 4 - Beta
Classifier: Intended Audience :: Developers
Classifier: License :: OSI Approved :: MIT License
Classifier: Operating System :: OS Independent
Classifier: Programming Language :: Python :: 3
Classifier: Programming Language :: Python :: 3.9
Classifier: Programming Language :: Python :: 3.10
Classifier: Programming Language :: Python :: 3.11
Classifier: Programming Language :: Python :: 3.12
Classifier: Programming Language :: Python :: 3.13
Classifier: Programming Language :: Python :: 3.14
Classifier: Topic :: Internet :: WWW/HTTP
Classifier: Topic :: Office/Business :: Financial
Classifier: Topic :: Software Development :: Libraries
Classifier: Topic :: Software Development :: Libraries :: Python Modules
Requires-Dist: pydantic (>=2.8.0,<3.0.0)
Requires-Dist: pydantic-settings (>=2.4.0,<3.0.0)
Requires-Dist: requests (>=2.31.0,<3.0.0)
Requires-Dist: typing-extensions (>=4.8.0,<5.0.0)
Project-URL: Bug Tracker, https://github.com/amitray007/shopify-partners-sdk/issues
Project-URL: Changelog, https://github.com/amitray007/shopify-partners-sdk/blob/main/CHANGELOG.md
Project-URL: Contributing, https://github.com/amitray007/shopify-partners-sdk/blob/main/CONTRIBUTING.md
Project-URL: Documentation, https://shopify-partners-sdk.readthedocs.io
Project-URL: Funding, https://github.com/sponsors/amitray007
Project-URL: Homepage, https://github.com/amitray007/shopify-partners-sdk
Project-URL: Repository, https://github.com/amitray007/shopify-partners-sdk
Project-URL: Source, https://github.com/amitray007/shopify-partners-sdk
